uw_iasystem/VERSION
uw_iasystem/__init__.py
uw_iasystem/dao.py
uw_iasystem/evaluation.py
uw_iasystem/exceptions.py
uw_iasystem/models.py
uw_iasystem/test.py
uw_iasystem/resources/iasystem_uw/file/api/v1/evaluation_course_number_100_curriculum_abbreviation_TRAIN_section_id_A_student_id_1033334_term_name_Spring_year_2013
uw_iasystem/resources/iasystem_uw/file/api/v1/evaluation_course_number_121_curriculum_abbreviation_PHYS_section_id_AQ_student_id_1033334_term_name_Spring_year_2013
uw_iasystem/resources/iasystem_uw/file/api/v1/evaluation_course_number_121_curriculum_abbreviation_PHYS_section_id_AQ_student_id_1233334_term_name_Spring_year_2013
uw_iasystem/resources/iasystem_uw/file/api/v1/evaluation_student_id_1033334_term_name_Autumn_year_2014
uw_iasystem/resources/iasystem_uw/file/api/v1/evaluation_term_name_Autumn_instructor_id_123456789_year_2014
uw_iasystem/resources/iasystem_uw/file/api/v1/evaluation_term_name_Winter_instructor_id_123456789_year_2015
uw_iasystem/resources/iasystem_uw/file/api/v1/evaluation_term_name_Winter_instructor_id_123456789_year_2015.http-headers
uw_iasystem/resources/iasystem_uw/file/api/v1/evaluation_term_name_Winter_instructor_id_123456789_year_2016
uw_iasystem/resources/iasystem_uw/file/api/v1/evaluation_term_name_Winter_instructor_id_123456789_year_2016.http-header
uw_iasystem/resources/iasystem_uw/file/api/v1/evaluation/132136
uw_iasystem/resources/iasystem_uw/file/api/v1/evaluation/141412
uw_iasystem/resources/iasystem_uwb/file/api/v1/evaluation_student_id_1033334_term_name_Autumn_year_2014
uw_iasystem/resources/iasystem_uweo_ap/file/api/v1/evaluation_term_name_Autumn_instructor_id_123456789_year_2013
uw_iasystem/resources/iasystem_uweo_ap/file/api/v1/evaluation_term_name_Summer_instructor_id_123456789_year_2013
uw_iasystem/resources/iasystem_uweo_ap/file/api/v1/evaluation/19253
uw_restclients_iasystem-1.1.5.dist-info/licenses/LICENSE
uw_restclients_iasystem-1.1.5.dist-info/METADATA
uw_restclients_iasystem-1.1.5.dist-info/WHEEL
uw_restclients_iasystem-1.1.5.dist-info/top_level.txt
uw_restclients_iasystem-1.1.5.dist-info/RECORD
